setup.cfg
setup.py
piton/__init__.py
piton/main.py
piton/node.py
piton/version.py
piton.egg-info/PKG-INFO
piton.egg-info/SOURCES.txt
piton.egg-info/dependency_links.txt
piton.egg-info/entry_points.txt
piton.egg-info/top_level.txt
piton/commands/__init__.py
piton/commands/init.py
piton/commands/install.py
piton/commands/list.py
piton/commands/outdated.py
piton/commands/path.py
piton/commands/prune.py
piton/commands/remove.py
piton/commands/run.py
piton/commands/update.py
piton/utils/__init__.py
piton/utils/command.py
piton/utils/display.py
piton/utils/installer.py
piton/utils/package_json.py
piton/utils/pypi_api.py
piton/utils/python_modules.py
piton/utils/sneak_config.py
piton/utils/tabulate.py
piton/utils/version.py